vehicle/__init__.py
vehicle/cfg/__init__.py
vehicle/cfg/backup.yaml
vehicle/cfg/default.yaml
vehicle/cfg/datasets/Argoverse.yaml
vehicle/cfg/datasets/DOTAv2.yaml
vehicle/cfg/datasets/GlobalWheat2020.yaml
vehicle/cfg/datasets/ImageNet.yaml
vehicle/cfg/datasets/Objects365.yaml
vehicle/cfg/datasets/SKU-110K.yaml
vehicle/cfg/datasets/VOC.yaml
vehicle/cfg/datasets/VisDrone.yaml
vehicle/cfg/datasets/coco-pose.yaml
vehicle/cfg/datasets/coco.yaml
vehicle/cfg/datasets/coco128-seg.yaml
vehicle/cfg/datasets/coco128.yaml
vehicle/cfg/datasets/coco8-pose.yaml
vehicle/cfg/datasets/coco8-seg.yaml
vehicle/cfg/datasets/coco8.yaml
vehicle/cfg/datasets/open-images-v7.yaml
vehicle/cfg/datasets/xView.yaml
vehicle/cfg/models/rt-detr/rtdetr-l.yaml
vehicle/cfg/models/rt-detr/rtdetr-x.yaml
vehicle/cfg/models/v3/yolov3-spp.yaml
vehicle/cfg/models/v3/yolov3-tiny.yaml
vehicle/cfg/models/v3/yolov3.yaml
vehicle/cfg/models/v5/yolov5-p6.yaml
vehicle/cfg/models/v5/yolov5.yaml
vehicle/cfg/models/v6/yolov6.yaml
vehicle/cfg/models/v8/yolov8-cls.yaml
vehicle/cfg/models/v8/yolov8-p2.yaml
vehicle/cfg/models/v8/yolov8-p6.yaml
vehicle/cfg/models/v8/yolov8-pose-p6.yaml
vehicle/cfg/models/v8/yolov8-pose.yaml
vehicle/cfg/models/v8/yolov8-rtdetr.yaml
vehicle/cfg/models/v8/yolov8-seg.yaml
vehicle/cfg/models/v8/yolov8.yaml
vehicle/cfg/trackers/botsort.yaml
vehicle/cfg/trackers/bytetrack.yaml
vehicle/data/__init__.py
vehicle/data/annotator.py
vehicle/data/augment.py
vehicle/data/base.py
vehicle/data/build.py
vehicle/data/converter.py
vehicle/data/dataset.py
vehicle/data/loaders.py
vehicle/data/utils.py
vehicle/engine/__init__.py
vehicle/engine/exporter.py
vehicle/engine/model.py
vehicle/engine/predictor.py
vehicle/engine/results.py
vehicle/engine/trainer.py
vehicle/engine/validator.py
vehicle/hub/__init__.py
vehicle/hub/auth.py
vehicle/hub/session.py
vehicle/hub/utils.py
vehicle/models/__init__.py
vehicle/models/fastsam/__init__.py
vehicle/models/fastsam/model.py
vehicle/models/fastsam/predict.py
zipvehicle-2.0.1.dist-info/LICENSE
zipvehicle-2.0.1.dist-info/METADATA
zipvehicle-2.0.1.dist-info/WHEEL
zipvehicle-2.0.1.dist-info/top_level.txt
zipvehicle-2.0.1.dist-info/RECORD
